tortoise_imagefield/__init__.py
tortoise_imagefield/config.py
tortoise_imagefield/fields.py
tortoise_imagefield/s3_cache.py
tortoise_imagefield/image_loader/__init__.py
tortoise_imagefield/image_loader/loader_adapter.py
tortoise_imagefield/image_loader/loader_interface.py
tortoise_imagefield/image_loader/loaders/__init__.py
tortoise_imagefield/image_loader/loaders/base64_loader.py
tortoise_imagefield/image_loader/loaders/upload_file_loader.py
tortoise_imagefield/image_loader/loaders/url_loader.py
tortoise_imagefield/storage/__init__.py
tortoise_imagefield/storage/crop_image.py
tortoise_imagefield/storage/storage_fabric.py
tortoise_imagefield/storage/storage_interface.py
tortoise_imagefield/storage/storage_types.py
tortoise_imagefield/storage/types/__init__.py
tortoise_imagefield/storage/types/local_storage.py
tortoise_imagefield/storage/types/s3_aws_storage.py
tortoise_imagefield-0.2.0.dist-info/licenses/LICENSE
tortoise_imagefield-0.2.0.dist-info/METADATA
tortoise_imagefield-0.2.0.dist-info/WHEEL
tortoise_imagefield-0.2.0.dist-info/top_level.txt
tortoise_imagefield-0.2.0.dist-info/RECORD
