Metadata-Version: 2.4
Name: tortoise-imagefield
Version: 0.2.0
Summary: Asynchronous Tortoise ORM field for handling image uploads with cropping, caching, and support for AWS S3 or local storage.
Author-email: Oleg Klishin <klishinoleg@gmail.com>
License: MIT
Requires-Python: >=3.10
License-File: LICENSE
Requires-Dist: tortoise-orm
Requires-Dist: pillow
Requires-Dist: python-dotenv
Requires-Dist: starlette
Requires-Dist: asgiref
Requires-Dist: python-slugify
Requires-Dist: aiohttp
Requires-Dist: aiofiles
Requires-Dist: aioboto3
Requires-Dist: aiocache
Provides-Extra: test
Requires-Dist: pytest; extra == "test"
Requires-Dist: pytest-asyncio; extra == "test"
Requires-Dist: fastapi; extra == "test"
Requires-Dist: httpx; extra == "test"
Dynamic: license-file
